doc/__init__.py
findatapy/__init__.py
findatapy/conf/__init__.py
findatapy/conf/all_econ_tickers.csv
findatapy/conf/base_depos_tickers_list.csv
findatapy/conf/configfindatapy.xlsm
findatapy/conf/econ_country_codes.csv
findatapy/conf/econ_tickers.xlsm
findatapy/conf/fx_forwards_tickers.csv
findatapy/conf/fx_forwards_tickers_maker.csv
findatapy/conf/fx_vol_tickers.csv
findatapy/conf/fx_vol_tickers_maker.csv
findatapy/conf/holidays_table.parquet
findatapy/conf/logging.conf
findatapy/conf/time_series_categories_fields.csv
findatapy/conf/time_series_fields_list.csv
findatapy/conf/time_series_tickers_list.csv
findatapy/market/__init__.py
findatapy/market/datavendor.py
findatapy/market/datavendorbbg.py
findatapy/market/datavendorcrypto.py
findatapy/market/datavendordatabento.py
findatapy/market/datavendorfred.py
findatapy/market/datavendorweb.py
findatapy/market/fxclsvolume.py
findatapy/market/ioengine.py
findatapy/market/market.py
findatapy/market/marketdatagenerator.py
findatapy/market/marketdatarequest.py
findatapy/timeseries/__init__.py
findatapy/timeseries/calculations.py
findatapy/timeseries/calendar.py
findatapy/timeseries/dataquality.py
findatapy/timeseries/filter.py
findatapy/timeseries/retstats.py
findatapy/timeseries/timezone.py
findatapy/util/__init__.py
findatapy/util/cachemanager.py
findatapy/util/commonman.py
findatapy/util/configmanager.py
findatapy/util/dataconstants.py
findatapy/util/fxconv.py
findatapy/util/loggermanager.py
findatapy/util/set_api_keys.py
findatapy/util/singleton.py
findatapy/util/swimpool.py
findatapy/util/tickerfactory.py
findatapy/util/twitter.py
findatapy_examples/__init__.py
findatapy_examples/alfred_example.py
findatapy_examples/arctic_example.py
findatapy_examples/arcticdb_example.py
findatapy_examples/arcticdb_md_example.py
findatapy_examples/cache_example.py
findatapy_examples/calculation_example.py
findatapy_examples/calendar_example.py
findatapy_examples/cryptocurrencies_example.py
findatapy_examples/cryptodata_example.py
findatapy-0.1.40.dist-info/LICENCE
findatapy-0.1.40.dist-info/METADATA
findatapy-0.1.40.dist-info/WHEEL
findatapy-0.1.40.dist-info/top_level.txt
findatapy-0.1.40.dist-info/RECORD
